head_context/__init__.py
head_context/context.py
head_context/jinja_ext.py
head_context/py.typed
head_context/utils.py
head_context-0.1.1.dist-info/WHEEL
head_context-0.1.1.dist-info/METADATA
head_context-0.1.1.dist-info/RECORD
