Metadata-Version: 2.1
Name: head-context
Version: 0.1.1
Summary: 
Home-page: https://github.com/rafales/head-context
License: MIT
Keywords: templating,jinja2
Author: Rafal Stozek
Author-email: rafal.stozek@gmail.com
Requires-Python: >=3.8,<4.0
Classifier: Development Status :: 3 - Alpha
Classifier: License :: OSI Approved :: MIT License
Classifier: Programming Language :: Python :: 3
Classifier: Programming Language :: Python :: 3.8
Classifier: Programming Language :: Python :: 3.9
Classifier: Programming Language :: Python :: 3.10
Classifier: Programming Language :: Python :: 3.11
Classifier: Programming Language :: Python :: 3
Classifier: Typing :: Typed
Requires-Dist: typing-extensions (>=4.4.0,<5.0.0)
Project-URL: Repository, https://github.com/rafales/head-context
